libname/__init__.py
libname/hello.py
helloev21-0.0.1.dist-info/METADATA
helloev21-0.0.1.dist-info/WHEEL
helloev21-0.0.1.dist-info/top_level.txt
helloev21-0.0.1.dist-info/RECORD
